tsutil/__init__.py
tsutil/main.py
tsutil/node_map.py
tsutil/node_printer.py
tsutil_py-0.1.0.dist-info/METADATA
tsutil_py-0.1.0.dist-info/WHEEL
tsutil_py-0.1.0.dist-info/entry_points.txt
tsutil_py-0.1.0.dist-info/RECORD
