Metadata-Version: 2.1
Name: tsutil-py
Version: 0.1.0
Summary: Syntax tree printer utility
Author-Email: Louis Maddox <louismmx@gmail.com>
License: MIT
Requires-Python: >=3.10
Requires-Dist: termcolor==2.3.0
Requires-Dist: tree-sitter>=0.22.3
Requires-Dist: tree-sitter-python>=0.21.0
Requires-Dist: tree-sitter-rust>=0.21.2
